{
  "name": "Fint",
  "logo": {
    "dark": "/logo/dark.svg",
    "light": "/logo/light.svg"
  },
  "favicon": "/favicon.svg",
  "colors": {
    "primary": "#0D9373",
    "light": "#07C983",
    "dark": "#0D9373",
    "anchors": {
      "from": "#0D9373",
      "to": "#07C983"
    }
  },
  "topbarLinks": [
    {
      "name": "Soporte",
      "url": "soporte@fint.app"
    }
  ],
  "tabs": [
    {
      "name": "API Referencia",
      "url": "api-reference"
    }
  ],
  "navigation": [
    {
      "group": "Comenzar",
      "pages": [
        "introduction"
      ]
    },
    {
      "group": "Contactos",
      "pages": [
        "docs/contact/introduction",
        "docs/contact/life-cycle"
      ]
    },
    {
      "group": "Webhooks",
      "pages": [
        "docs/webhooks/1_introduction",
        "docs/webhooks/2_structure",
        "docs/webhooks/3_events",
        "docs/webhooks/4_security"
      ]
    },
    {
      "group": "Contactos",
      "pages": [
        "api-reference/contactos/crear-un-nuevo-contacto",
        "api-reference/contactos/obtener-contacto-por-id",
        "api-reference/contactos/eliminar-contacto-por-id",
        "api-reference/contactos/obtener-contacto-por-referencia-externa"
      ]
    },
    {
      "group": "Facturas",
      "pages": [
        "api-reference/facturas/crear-una-nueva-factura"
      ]
    },
    {
      "group": "Pagos",
      "pages": [
        "api-reference/pagos/obtener-pago-por-id"
      ]
    },
    {
      "group": "Webhook",
      "pages": [
        "api-reference/webhook/obtener-lista-de-webhooks",
        "api-reference/webhook/crear-un-nuevo-webhook",
        "api-reference/webhook/obtener-webhook-por-id",
        "api-reference/webhook/actualizar-webhook-por-id",
        "api-reference/webhook/eliminar-webhook-por-id"
      ]
    }
  ],
  "footerSocials": {
    "linkedin": "https://www.linkedin.com/company/fint-latam/"
  },
  "openapi": "https://dev.api.fint.app/api/v1/api-docs"
}